build/lib/build/lib/build/lib/build/lib/libsearch/__init__.py
build/lib/build/lib/build/lib/build/lib/libsearch/blind_search.py
build/lib/build/lib/build/lib/build/lib/libsearch/data_structs.py
build/lib/build/lib/build/lib/build/lib/libsearch/informed_search.py
build/lib/build/lib/build/lib/libsearch/__init__.py
build/lib/build/lib/build/lib/libsearch/blind_search.py
build/lib/build/lib/build/lib/libsearch/data_structs.py
build/lib/build/lib/build/lib/libsearch/informed_search.py
build/lib/build/lib/build/lib/libsearch/test/__init__.py
build/lib/build/lib/build/lib/libsearch/test/test_graph.py
build/lib/build/lib/build/lib/libsearch/test/test_maze.py
build/lib/build/lib/libsearch/__init__.py
build/lib/build/lib/libsearch/blind_search.py
build/lib/build/lib/libsearch/data_structs.py
build/lib/build/lib/libsearch/informed_search.py
build/lib/build/lib/libsearch/test/__init__.py
build/lib/build/lib/libsearch/test/test_graph.py
build/lib/build/lib/libsearch/test/test_maze.py
build/lib/examples/graph.py
build/lib/examples/maze.py
build/lib/libsearch/__init__.py
build/lib/libsearch/blind_search.py
build/lib/libsearch/data_structs.py
build/lib/libsearch/informed_search.py
build/lib/libsearch/test/__init__.py
build/lib/libsearch/test/test_graph.py
build/lib/libsearch/test/test_maze.py
examples/graph.py
examples/maze.py
libsearch/__init__.py
libsearch/blind_search.py
libsearch/data_structs.py
libsearch/informed_search.py
libsearch/test/__init__.py
libsearch/test/test_graph.py
libsearch/test/test_maze.py
libsearch-0.0.5.post1.dist-info/METADATA
libsearch-0.0.5.post1.dist-info/WHEEL
libsearch-0.0.5.post1.dist-info/top_level.txt
libsearch-0.0.5.post1.dist-info/RECORD
