Metadata-Version: 2.1
Name: libsearch
Version: 0.0.5.post1
Summary: A library of searh algorithms
Home-page: https://github.com/Johnbin89/SearchLibrary
Author: Ioannis Biniaris
Author-email: john_biniaris@hotmail.com
License: UNKNOWN
Platform: UNKNOWN
Classifier: Programming Language :: Python :: 3
Classifier: License :: OSI Approved :: MIT License
Classifier: Operating System :: OS Independent
Requires-Python: >=3.6
